rustc_t_x64_win_msvc_nightly_p1/__init__.py
rustc_t_x64_win_msvc_nightly_p1/data/COPYRIGHT
rustc_t_x64_win_msvc_nightly_p1/data/LICENSE-APACHE
rustc_t_x64_win_msvc_nightly_p1/data/LICENSE-MIT
rustc_t_x64_win_msvc_nightly_p1/data/README.md
rustc_t_x64_win_msvc_nightly_p1/data/builder-config
rustc_t_x64_win_msvc_nightly_p1/data/components
rustc_t_x64_win_msvc_nightly_p1/data/git-commit-hash
rustc_t_x64_win_msvc_nightly_p1/data/git-commit-info
rustc_t_x64_win_msvc_nightly_p1/data/install.sh
rustc_t_x64_win_msvc_nightly_p1/data/rust-installer-version
rustc_t_x64_win_msvc_nightly_p1/data/version
rustc_t_x64_win_msvc_nightly_p1/data/rustc/manifest.in
rustc_t_x64_win_msvc_nightly_p1/data/rustc/lib/rustlib/x86_64-pc-windows-msvc/bin/rust-objcopy.exe
rustc_t_x64_win_msvc_nightly_p1/data/rustc/lib/rustlib/x86_64-pc-windows-msvc/bin/wasm-component-ld.exe
rustc_t_x64_win_msvc_nightly_p1/data/rustc/lib/rustlib/x86_64-pc-windows-msvc/bin/wasm-component-ld.pdb
rustc_t_x64_win_msvc_nightly_p1/data/rustc/share/doc/rust/COPYRIGHT-library.html
rustc_t_x64_win_msvc_nightly_p1/data/rustc/share/doc/rust/COPYRIGHT.html
rustc_t_x64_win_msvc_nightly_p1/data/rustc/share/doc/rust/README.md
rustc_t_x64_win_msvc_nightly_p1/data/rustc/share/doc/rust/licenses/Apache-2.0.txt
rustc_t_x64_win_msvc_nightly_p1/data/rustc/share/doc/rust/licenses/BSD-2-Clause.txt
rustc_t_x64_win_msvc_nightly_p1/data/rustc/share/doc/rust/licenses/CC-BY-SA-4.0.txt
rustc_t_x64_win_msvc_nightly_p1/data/rustc/share/doc/rust/licenses/GCC-exception-3.1.txt
rustc_t_x64_win_msvc_nightly_p1/data/rustc/share/doc/rust/licenses/GPL-2.0-only.txt
rustc_t_x64_win_msvc_nightly_p1/data/rustc/share/doc/rust/licenses/GPL-3.0-or-later.txt
rustc_t_x64_win_msvc_nightly_p1/data/rustc/share/doc/rust/licenses/ISC.txt
rustc_t_x64_win_msvc_nightly_p1/data/rustc/share/doc/rust/licenses/LLVM-exception.txt
rustc_t_x64_win_msvc_nightly_p1/data/rustc/share/doc/rust/licenses/MIT.txt
rustc_t_x64_win_msvc_nightly_p1-1.91.0.dist-info/METADATA
rustc_t_x64_win_msvc_nightly_p1-1.91.0.dist-info/WHEEL
rustc_t_x64_win_msvc_nightly_p1-1.91.0.dist-info/top_level.txt
rustc_t_x64_win_msvc_nightly_p1-1.91.0.dist-info/RECORD
